<?xml version="1.0" encoding="UTF-8"?>
<spirit:component xmlns:xilinx="http://www.xilinx.com" xmlns:spirit="http://www.spiritconsortium.org/XMLSchema/SPIRIT/1685-2009" xmlns:xsi="http://www.w3.org/2001/XMLSchema-instance">
  <spirit:vendor>xilinx.com</spirit:vendor>
  <spirit:library>ip</spirit:library>
  <spirit:name>audio_clock_recovery_unit</spirit:name>
  <spirit:version>1.0</spirit:version>
  <spirit:busInterfaces>
    <spirit:busInterface>
      <spirit:name>s_axi_ctrl</spirit:name>
      <spirit:busType spirit:vendor="xilinx.com" spirit:library="interface" spirit:name="aximm" spirit:version="1.0"/>
      <spirit:abstractionType spirit:vendor="xilinx.com" spirit:library="interface" spirit:name="aximm_rtl" spirit:version="1.0"/>
      <spirit:slave/>
      <spirit:portMaps>
        <spirit:portMap>
          <spirit:logicalPort>
            <spirit:name>ARADDR</spirit:name>
          </spirit:logicalPort>
          <spirit:physicalPort>
            <spirit:name>s_axi_ctrl_araddr</spirit:name>
          </spirit:physicalPort>
        </spirit:portMap>
        <spirit:portMap>
          <spirit:logicalPort>
            <spirit:name>ARREADY</spirit:name>
          </spirit:logicalPort>
          <spirit:physicalPort>
            <spirit:name>s_axi_ctrl_arready</spirit:name>
          </spirit:physicalPort>
        </spirit:portMap>
        <spirit:portMap>
          <spirit:logicalPort>
            <spirit:name>ARVALID</spirit:name>
          </spirit:logicalPort>
          <spirit:physicalPort>
            <spirit:name>s_axi_ctrl_arvalid</spirit:name>
          </spirit:physicalPort>
        </spirit:portMap>
        <spirit:portMap>
          <spirit:logicalPort>
            <spirit:name>AWADDR</spirit:name>
          </spirit:logicalPort>
          <spirit:physicalPort>
            <spirit:name>s_axi_ctrl_awaddr</spirit:name>
          </spirit:physicalPort>
        </spirit:portMap>
        <spirit:portMap>
          <spirit:logicalPort>
            <spirit:name>AWREADY</spirit:name>
          </spirit:logicalPort>
          <spirit:physicalPort>
            <spirit:name>s_axi_ctrl_awready</spirit:name>
          </spirit:physicalPort>
        </spirit:portMap>
        <spirit:portMap>
          <spirit:logicalPort>
            <spirit:name>AWVALID</spirit:name>
          </spirit:logicalPort>
          <spirit:physicalPort>
            <spirit:name>s_axi_ctrl_awvalid</spirit:name>
          </spirit:physicalPort>
        </spirit:portMap>
        <spirit:portMap>
          <spirit:logicalPort>
            <spirit:name>BREADY</spirit:name>
          </spirit:logicalPort>
          <spirit:physicalPort>
            <spirit:name>s_axi_ctrl_bready</spirit:name>
          </spirit:physicalPort>
        </spirit:portMap>
        <spirit:portMap>
          <spirit:logicalPort>
            <spirit:name>BRESP</spirit:name>
          </spirit:logicalPort>
          <spirit:physicalPort>
            <spirit:name>s_axi_ctrl_bresp</spirit:name>
          </spirit:physicalPort>
        </spirit:portMap>
        <spirit:portMap>
          <spirit:logicalPort>
            <spirit:name>BVALID</spirit:name>
          </spirit:logicalPort>
          <spirit:physicalPort>
            <spirit:name>s_axi_ctrl_bvalid</spirit:name>
          </spirit:physicalPort>
        </spirit:portMap>
        <spirit:portMap>
          <spirit:logicalPort>
            <spirit:name>RDATA</spirit:name>
          </spirit:logicalPort>
          <spirit:physicalPort>
            <spirit:name>s_axi_ctrl_rdata</spirit:name>
          </spirit:physicalPort>
        </spirit:portMap>
        <spirit:portMap>
          <spirit:logicalPort>
            <spirit:name>RREADY</spirit:name>
          </spirit:logicalPort>
          <spirit:physicalPort>
            <spirit:name>s_axi_ctrl_rready</spirit:name>
          </spirit:physicalPort>
        </spirit:portMap>
        <spirit:portMap>
          <spirit:logicalPort>
            <spirit:name>RRESP</spirit:name>
          </spirit:logicalPort>
          <spirit:physicalPort>
            <spirit:name>s_axi_ctrl_rresp</spirit:name>
          </spirit:physicalPort>
        </spirit:portMap>
        <spirit:portMap>
          <spirit:logicalPort>
            <spirit:name>RVALID</spirit:name>
          </spirit:logicalPort>
          <spirit:physicalPort>
            <spirit:name>s_axi_ctrl_rvalid</spirit:name>
          </spirit:physicalPort>
        </spirit:portMap>
        <spirit:portMap>
          <spirit:logicalPort>
            <spirit:name>WDATA</spirit:name>
          </spirit:logicalPort>
          <spirit:physicalPort>
            <spirit:name>s_axi_ctrl_wdata</spirit:name>
          </spirit:physicalPort>
        </spirit:portMap>
        <spirit:portMap>
          <spirit:logicalPort>
            <spirit:name>WREADY</spirit:name>
          </spirit:logicalPort>
          <spirit:physicalPort>
            <spirit:name>s_axi_ctrl_wready</spirit:name>
          </spirit:physicalPort>
        </spirit:portMap>
        <spirit:portMap>
          <spirit:logicalPort>
            <spirit:name>WVALID</spirit:name>
          </spirit:logicalPort>
          <spirit:physicalPort>
            <spirit:name>s_axi_ctrl_wvalid</spirit:name>
          </spirit:physicalPort>
        </spirit:portMap>
      </spirit:portMaps>
    </spirit:busInterface>
    <spirit:busInterface>
      <spirit:name>s_axi_ctrl_aresetn</spirit:name>
      <spirit:busType spirit:vendor="xilinx.com" spirit:library="signal" spirit:name="reset" spirit:version="1.0"/>
      <spirit:abstractionType spirit:vendor="xilinx.com" spirit:library="signal" spirit:name="reset_rtl" spirit:version="1.0"/>
      <spirit:slave/>
      <spirit:portMaps>
        <spirit:portMap>
          <spirit:logicalPort>
            <spirit:name>RST</spirit:name>
          </spirit:logicalPort>
          <spirit:physicalPort>
            <spirit:name>s_axi_ctrl_aresetn</spirit:name>
          </spirit:physicalPort>
        </spirit:portMap>
      </spirit:portMaps>
      <spirit:parameters>
        <spirit:parameter>
          <spirit:name>POLARITY</spirit:name>
          <spirit:value spirit:id="BUSIFPARAM_VALUE.S_AXI_CTRL_ARESETN.POLARITY">ACTIVE_LOW</spirit:value>
        </spirit:parameter>
      </spirit:parameters>
    </spirit:busInterface>
    <spirit:busInterface>
      <spirit:name>s_axi_ctrl_aclk</spirit:name>
      <spirit:busType spirit:vendor="xilinx.com" spirit:library="signal" spirit:name="clock" spirit:version="1.0"/>
      <spirit:abstractionType spirit:vendor="xilinx.com" spirit:library="signal" spirit:name="clock_rtl" spirit:version="1.0"/>
      <spirit:slave/>
      <spirit:portMaps>
        <spirit:portMap>
          <spirit:logicalPort>
            <spirit:name>CLK</spirit:name>
          </spirit:logicalPort>
          <spirit:physicalPort>
            <spirit:name>s_axi_ctrl_aclk</spirit:name>
          </spirit:physicalPort>
        </spirit:portMap>
      </spirit:portMaps>
      <spirit:parameters>
        <spirit:parameter>
          <spirit:name>ASSOCIATED_BUSIF</spirit:name>
          <spirit:value spirit:id="BUSIFPARAM_VALUE.S_AXI_CTRL_ACLK.ASSOCIATED_BUSIF">s_axi_ctrl</spirit:value>
        </spirit:parameter>
        <spirit:parameter>
          <spirit:name>ASSOCIATED_RESET</spirit:name>
          <spirit:value spirit:id="BUSIFPARAM_VALUE.S_AXI_CTRL_ACLK.ASSOCIATED_RESET">s_axi_ctrl_aresetn</spirit:value>
        </spirit:parameter>
      </spirit:parameters>
    </spirit:busInterface>
    <spirit:busInterface>
      <spirit:name>irq</spirit:name>
      <spirit:busType spirit:vendor="xilinx.com" spirit:library="signal" spirit:name="interrupt" spirit:version="1.0"/>
      <spirit:abstractionType spirit:vendor="xilinx.com" spirit:library="signal" spirit:name="interrupt_rtl" spirit:version="1.0"/>
      <spirit:master/>
      <spirit:portMaps>
        <spirit:portMap>
          <spirit:logicalPort>
            <spirit:name>INTERRUPT</spirit:name>
          </spirit:logicalPort>
          <spirit:physicalPort>
            <spirit:name>irq</spirit:name>
          </spirit:physicalPort>
        </spirit:portMap>
      </spirit:portMaps>
      <spirit:parameters>
        <spirit:parameter>
          <spirit:name>SENSITIVITY</spirit:name>
          <spirit:value spirit:id="BUSIFPARAM_VALUE.IRQ.SENSITIVITY">LEVEL_HIGH</spirit:value>
        </spirit:parameter>
      </spirit:parameters>
    </spirit:busInterface>
    <spirit:busInterface>
      <spirit:name>ref_clk_resetn</spirit:name>
      <spirit:busType spirit:vendor="xilinx.com" spirit:library="signal" spirit:name="reset" spirit:version="1.0"/>
      <spirit:abstractionType spirit:vendor="xilinx.com" spirit:library="signal" spirit:name="reset_rtl" spirit:version="1.0"/>
      <spirit:slave/>
      <spirit:portMaps>
        <spirit:portMap>
          <spirit:logicalPort>
            <spirit:name>RST</spirit:name>
          </spirit:logicalPort>
          <spirit:physicalPort>
            <spirit:name>ref_clk_resetn</spirit:name>
          </spirit:physicalPort>
        </spirit:portMap>
      </spirit:portMaps>
      <spirit:parameters>
        <spirit:parameter>
          <spirit:name>POLARITY</spirit:name>
          <spirit:value spirit:id="BUSIFPARAM_VALUE.REF_CLK_RESETN.POLARITY">ACTIVE_LOW</spirit:value>
        </spirit:parameter>
      </spirit:parameters>
    </spirit:busInterface>
    <spirit:busInterface>
      <spirit:name>acr_resetn</spirit:name>
      <spirit:busType spirit:vendor="xilinx.com" spirit:library="signal" spirit:name="reset" spirit:version="1.0"/>
      <spirit:abstractionType spirit:vendor="xilinx.com" spirit:library="signal" spirit:name="reset_rtl" spirit:version="1.0"/>
      <spirit:slave/>
      <spirit:portMaps>
        <spirit:portMap>
          <spirit:logicalPort>
            <spirit:name>RST</spirit:name>
          </spirit:logicalPort>
          <spirit:physicalPort>
            <spirit:name>acr_resetn</spirit:name>
          </spirit:physicalPort>
        </spirit:portMap>
      </spirit:portMaps>
      <spirit:parameters>
        <spirit:parameter>
          <spirit:name>POLARITY</spirit:name>
          <spirit:value spirit:id="BUSIFPARAM_VALUE.ACR_RESETN.POLARITY">ACTIVE_LOW</spirit:value>
        </spirit:parameter>
      </spirit:parameters>
    </spirit:busInterface>
    <spirit:busInterface>
      <spirit:name>ref_clk</spirit:name>
      <spirit:busType spirit:vendor="xilinx.com" spirit:library="signal" spirit:name="clock" spirit:version="1.0"/>
      <spirit:abstractionType spirit:vendor="xilinx.com" spirit:library="signal" spirit:name="clock_rtl" spirit:version="1.0"/>
      <spirit:slave/>
      <spirit:portMaps>
        <spirit:portMap>
          <spirit:logicalPort>
            <spirit:name>CLK</spirit:name>
          </spirit:logicalPort>
          <spirit:physicalPort>
            <spirit:name>ref_clk</spirit:name>
          </spirit:physicalPort>
        </spirit:portMap>
      </spirit:portMaps>
      <spirit:parameters>
        <spirit:parameter>
          <spirit:name>ASSOCIATED_RESET</spirit:name>
          <spirit:value spirit:id="BUSIFPARAM_VALUE.REF_CLK.ASSOCIATED_RESET">ref_clk_resetn</spirit:value>
        </spirit:parameter>
      </spirit:parameters>
    </spirit:busInterface>
    <spirit:busInterface>
      <spirit:name>acr_clk</spirit:name>
      <spirit:busType spirit:vendor="xilinx.com" spirit:library="signal" spirit:name="clock" spirit:version="1.0"/>
      <spirit:abstractionType spirit:vendor="xilinx.com" spirit:library="signal" spirit:name="clock_rtl" spirit:version="1.0"/>
      <spirit:slave/>
      <spirit:portMaps>
        <spirit:portMap>
          <spirit:logicalPort>
            <spirit:name>CLK</spirit:name>
          </spirit:logicalPort>
          <spirit:physicalPort>
            <spirit:name>acr_clk</spirit:name>
          </spirit:physicalPort>
        </spirit:portMap>
      </spirit:portMaps>
      <spirit:parameters>
        <spirit:parameter>
          <spirit:name>ASSOCIATED_RESET</spirit:name>
          <spirit:value spirit:id="BUSIFPARAM_VALUE.ACR_CLK.ASSOCIATED_RESET">acr_resetn</spirit:value>
        </spirit:parameter>
      </spirit:parameters>
    </spirit:busInterface>
    <spirit:busInterface>
      <spirit:name>aud_mclk</spirit:name>
      <spirit:busType spirit:vendor="xilinx.com" spirit:library="signal" spirit:name="clock" spirit:version="1.0"/>
      <spirit:abstractionType spirit:vendor="xilinx.com" spirit:library="signal" spirit:name="clock_rtl" spirit:version="1.0"/>
      <spirit:slave/>
      <spirit:portMaps>
        <spirit:portMap>
          <spirit:logicalPort>
            <spirit:name>CLK</spirit:name>
          </spirit:logicalPort>
          <spirit:physicalPort>
            <spirit:name>aud_mclk</spirit:name>
          </spirit:physicalPort>
        </spirit:portMap>
      </spirit:portMaps>
      <spirit:parameters>
        <spirit:parameter>
          <spirit:name>ASSOCIATED_RESET</spirit:name>
          <spirit:value spirit:id="BUSIFPARAM_VALUE.AUD_MCLK.ASSOCIATED_RESET">aud_mrst</spirit:value>
        </spirit:parameter>
      </spirit:parameters>
    </spirit:busInterface>
    <spirit:busInterface>
      <spirit:name>aud_mrst</spirit:name>
      <spirit:busType spirit:vendor="xilinx.com" spirit:library="signal" spirit:name="reset" spirit:version="1.0"/>
      <spirit:abstractionType spirit:vendor="xilinx.com" spirit:library="signal" spirit:name="reset_rtl" spirit:version="1.0"/>
      <spirit:slave/>
      <spirit:portMaps>
        <spirit:portMap>
          <spirit:logicalPort>
            <spirit:name>RST</spirit:name>
          </spirit:logicalPort>
          <spirit:physicalPort>
            <spirit:name>aud_mrst</spirit:name>
          </spirit:physicalPort>
        </spirit:portMap>
      </spirit:portMaps>
      <spirit:parameters>
        <spirit:parameter>
          <spirit:name>POLARITY</spirit:name>
          <spirit:value spirit:id="BUSIFPARAM_VALUE.AUD_MRST.POLARITY">ACTIVE_HIGH</spirit:value>
        </spirit:parameter>
      </spirit:parameters>
    </spirit:busInterface>
  </spirit:busInterfaces>
  <spirit:model>
    <spirit:views>
      <spirit:view>
        <spirit:name>xilinx_xpgui</spirit:name>
        <spirit:displayName>UI Layout</spirit:displayName>
        <spirit:envIdentifier>:vivado.xilinx.com:xgui.ui</spirit:envIdentifier>
        <spirit:fileSetRef>
          <spirit:localName>xilinx_xpgui_view_fileset</spirit:localName>
        </spirit:fileSetRef>
        <spirit:parameters>
          <spirit:parameter>
            <spirit:name>viewChecksum</spirit:name>
            <spirit:value>f64a5dae</spirit:value>
          </spirit:parameter>
        </spirit:parameters>
      </spirit:view>
      <spirit:view>
        <spirit:name>xilinx_anylanguagebehavioralsimulation</spirit:name>
        <spirit:displayName>Simulation</spirit:displayName>
        <spirit:envIdentifier>:vivado.xilinx.com:simulation</spirit:envIdentifier>
        <spirit:language>Verilog</spirit:language>
        <spirit:modelName>audio_clock_recovery_v1_0</spirit:modelName>
        <spirit:fileSetRef>
          <spirit:localName>xilinx_anylanguagebehavioralsimulation_view_fileset</spirit:localName>
        </spirit:fileSetRef>
        <spirit:parameters>
          <spirit:parameter>
            <spirit:name>viewChecksum</spirit:name>
            <spirit:value>ebd537ff</spirit:value>
          </spirit:parameter>
        </spirit:parameters>
      </spirit:view>
      <spirit:view>
        <spirit:name>xilinx_anylanguagesynthesis</spirit:name>
        <spirit:displayName>Synthesis</spirit:displayName>
        <spirit:envIdentifier>:vivado.xilinx.com:synthesis</spirit:envIdentifier>
        <spirit:language>Verilog</spirit:language>
        <spirit:modelName>audio_clock_recovery_v1_0</spirit:modelName>
        <spirit:fileSetRef>
          <spirit:localName>xilinx_anylanguagesynthesis_view_fileset</spirit:localName>
        </spirit:fileSetRef>
        <spirit:parameters>
          <spirit:parameter>
            <spirit:name>viewChecksum</spirit:name>
            <spirit:value>3f630e5d</spirit:value>
          </spirit:parameter>
        </spirit:parameters>
      </spirit:view>
    </spirit:views>
    <spirit:ports>
      <spirit:port>
        <spirit:name>s_axi_ctrl_aclk</spirit:name>
        <spirit:wire>
          <spirit:direction>in</spirit:direction>
          <spirit:wireTypeDefs>
            <spirit:wireTypeDef>
              <spirit:typeName>std_logic</spirit:typeName>
              <spirit:viewNameRef>xilinx_anylanguagesynthesis</spirit:viewNameRef>
              <spirit:viewNameRef>xilinx_anylanguagebehavioralsimulation</spirit:viewNameRef>
            </spirit:wireTypeDef>
          </spirit:wireTypeDefs>
        </spirit:wire>
      </spirit:port>
      <spirit:port>
        <spirit:name>s_axi_ctrl_aresetn</spirit:name>
        <spirit:wire>
          <spirit:direction>in</spirit:direction>
          <spirit:wireTypeDefs>
            <spirit:wireTypeDef>
              <spirit:typeName>std_logic</spirit:typeName>
              <spirit:viewNameRef>xilinx_anylanguagesynthesis</spirit:viewNameRef>
              <spirit:viewNameRef>xilinx_anylanguagebehavioralsimulation</spirit:viewNameRef>
            </spirit:wireTypeDef>
          </spirit:wireTypeDefs>
        </spirit:wire>
      </spirit:port>
      <spirit:port>
        <spirit:name>ref_clk</spirit:name>
        <spirit:wire>
          <spirit:direction>in</spirit:direction>
          <spirit:wireTypeDefs>
            <spirit:wireTypeDef>
              <spirit:typeName>std_logic</spirit:typeName>
              <spirit:viewNameRef>xilinx_anylanguagesynthesis</spirit:viewNameRef>
              <spirit:viewNameRef>xilinx_anylanguagebehavioralsimulation</spirit:viewNameRef>
            </spirit:wireTypeDef>
          </spirit:wireTypeDefs>
        </spirit:wire>
      </spirit:port>
      <spirit:port>
        <spirit:name>ref_clk_resetn</spirit:name>
        <spirit:wire>
          <spirit:direction>in</spirit:direction>
          <spirit:wireTypeDefs>
            <spirit:wireTypeDef>
              <spirit:typeName>std_logic</spirit:typeName>
              <spirit:viewNameRef>xilinx_anylanguagesynthesis</spirit:viewNameRef>
              <spirit:viewNameRef>xilinx_anylanguagebehavioralsimulation</spirit:viewNameRef>
            </spirit:wireTypeDef>
          </spirit:wireTypeDefs>
        </spirit:wire>
      </spirit:port>
      <spirit:port>
        <spirit:name>acr_clk</spirit:name>
        <spirit:wire>
          <spirit:direction>in</spirit:direction>
          <spirit:wireTypeDefs>
            <spirit:wireTypeDef>
              <spirit:typeName>std_logic</spirit:typeName>
              <spirit:viewNameRef>xilinx_anylanguagesynthesis</spirit:viewNameRef>
              <spirit:viewNameRef>xilinx_anylanguagebehavioralsimulation</spirit:viewNameRef>
            </spirit:wireTypeDef>
          </spirit:wireTypeDefs>
        </spirit:wire>
      </spirit:port>
      <spirit:port>
        <spirit:name>acr_resetn</spirit:name>
        <spirit:wire>
          <spirit:direction>in</spirit:direction>
          <spirit:wireTypeDefs>
            <spirit:wireTypeDef>
              <spirit:typeName>std_logic</spirit:typeName>
              <spirit:viewNameRef>xilinx_anylanguagesynthesis</spirit:viewNameRef>
              <spirit:viewNameRef>xilinx_anylanguagebehavioralsimulation</spirit:viewNameRef>
            </spirit:wireTypeDef>
          </spirit:wireTypeDefs>
        </spirit:wire>
      </spirit:port>
      <spirit:port>
        <spirit:name>aud_mclk</spirit:name>
        <spirit:wire>
          <spirit:direction>in</spirit:direction>
          <spirit:wireTypeDefs>
            <spirit:wireTypeDef>
              <spirit:typeName>std_logic</spirit:typeName>
              <spirit:viewNameRef>xilinx_anylanguagesynthesis</spirit:viewNameRef>
              <spirit:viewNameRef>xilinx_anylanguagebehavioralsimulation</spirit:viewNameRef>
            </spirit:wireTypeDef>
          </spirit:wireTypeDefs>
        </spirit:wire>
      </spirit:port>
      <spirit:port>
        <spirit:name>aud_mrst</spirit:name>
        <spirit:wire>
          <spirit:direction>in</spirit:direction>
          <spirit:wireTypeDefs>
            <spirit:wireTypeDef>
              <spirit:typeName>std_logic</spirit:typeName>
              <spirit:viewNameRef>xilinx_anylanguagesynthesis</spirit:viewNameRef>
              <spirit:viewNameRef>xilinx_anylanguagebehavioralsimulation</spirit:viewNameRef>
            </spirit:wireTypeDef>
          </spirit:wireTypeDefs>
        </spirit:wire>
      </spirit:port>
      <spirit:port>
        <spirit:name>s_axi_ctrl_awvalid</spirit:name>
        <spirit:wire>
          <spirit:direction>in</spirit:direction>
          <spirit:wireTypeDefs>
            <spirit:wireTypeDef>
              <spirit:typeName>std_logic</spirit:typeName>
              <spirit:viewNameRef>xilinx_anylanguagesynthesis</spirit:viewNameRef>
              <spirit:viewNameRef>xilinx_anylanguagebehavioralsimulation</spirit:viewNameRef>
            </spirit:wireTypeDef>
          </spirit:wireTypeDefs>
          <spirit:driver>
            <spirit:defaultValue spirit:format="long">0</spirit:defaultValue>
          </spirit:driver>
        </spirit:wire>
      </spirit:port>
      <spirit:port>
        <spirit:name>s_axi_ctrl_awready</spirit:name>
        <spirit:wire>
          <spirit:direction>out</spirit:direction>
          <spirit:wireTypeDefs>
            <spirit:wireTypeDef>
              <spirit:typeName>std_logic</spirit:typeName>
              <spirit:viewNameRef>xilinx_anylanguagesynthesis</spirit:viewNameRef>
              <spirit:viewNameRef>xilinx_anylanguagebehavioralsimulation</spirit:viewNameRef>
            </spirit:wireTypeDef>
          </spirit:wireTypeDefs>
        </spirit:wire>
      </spirit:port>
      <spirit:port>
        <spirit:name>s_axi_ctrl_awaddr</spirit:name>
        <spirit:wire>
          <spirit:direction>in</spirit:direction>
          <spirit:vector>
            <spirit:left spirit:format="long">7</spirit:left>
            <spirit:right spirit:format="long">0</spirit:right>
          </spirit:vector>
          <spirit:wireTypeDefs>
            <spirit:wireTypeDef>
              <spirit:typeName>std_logic_vector</spirit:typeName>
              <spirit:viewNameRef>xilinx_anylanguagesynthesis</spirit:viewNameRef>
              <spirit:viewNameRef>xilinx_anylanguagebehavioralsimulation</spirit:viewNameRef>
            </spirit:wireTypeDef>
          </spirit:wireTypeDefs>
          <spirit:driver>
            <spirit:defaultValue spirit:format="long">0</spirit:defaultValue>
          </spirit:driver>
        </spirit:wire>
      </spirit:port>
      <spirit:port>
        <spirit:name>s_axi_ctrl_wvalid</spirit:name>
        <spirit:wire>
          <spirit:direction>in</spirit:direction>
          <spirit:wireTypeDefs>
            <spirit:wireTypeDef>
              <spirit:typeName>std_logic</spirit:typeName>
              <spirit:viewNameRef>xilinx_anylanguagesynthesis</spirit:viewNameRef>
              <spirit:viewNameRef>xilinx_anylanguagebehavioralsimulation</spirit:viewNameRef>
            </spirit:wireTypeDef>
          </spirit:wireTypeDefs>
          <spirit:driver>
            <spirit:defaultValue spirit:format="long">0</spirit:defaultValue>
          </spirit:driver>
        </spirit:wire>
      </spirit:port>
      <spirit:port>
        <spirit:name>s_axi_ctrl_wready</spirit:name>
        <spirit:wire>
          <spirit:direction>out</spirit:direction>
          <spirit:wireTypeDefs>
            <spirit:wireTypeDef>
              <spirit:typeName>std_logic</spirit:typeName>
              <spirit:viewNameRef>xilinx_anylanguagesynthesis</spirit:viewNameRef>
              <spirit:viewNameRef>xilinx_anylanguagebehavioralsimulation</spirit:viewNameRef>
            </spirit:wireTypeDef>
          </spirit:wireTypeDefs>
        </spirit:wire>
      </spirit:port>
      <spirit:port>
        <spirit:name>s_axi_ctrl_wdata</spirit:name>
        <spirit:wire>
          <spirit:direction>in</spirit:direction>
          <spirit:vector>
            <spirit:left spirit:format="long">31</spirit:left>
            <spirit:right spirit:format="long">0</spirit:right>
          </spirit:vector>
          <spirit:wireTypeDefs>
            <spirit:wireTypeDef>
              <spirit:typeName>std_logic_vector</spirit:typeName>
              <spirit:viewNameRef>xilinx_anylanguagesynthesis</spirit:viewNameRef>
              <spirit:viewNameRef>xilinx_anylanguagebehavioralsimulation</spirit:viewNameRef>
            </spirit:wireTypeDef>
          </spirit:wireTypeDefs>
          <spirit:driver>
            <spirit:defaultValue spirit:format="long">0</spirit:defaultValue>
          </spirit:driver>
        </spirit:wire>
      </spirit:port>
      <spirit:port>
        <spirit:name>s_axi_ctrl_bvalid</spirit:name>
        <spirit:wire>
          <spirit:direction>out</spirit:direction>
          <spirit:wireTypeDefs>
            <spirit:wireTypeDef>
              <spirit:typeName>std_logic</spirit:typeName>
              <spirit:viewNameRef>xilinx_anylanguagesynthesis</spirit:viewNameRef>
              <spirit:viewNameRef>xilinx_anylanguagebehavioralsimulation</spirit:viewNameRef>
            </spirit:wireTypeDef>
          </spirit:wireTypeDefs>
        </spirit:wire>
      </spirit:port>
      <spirit:port>
        <spirit:name>s_axi_ctrl_bready</spirit:name>
        <spirit:wire>
          <spirit:direction>in</spirit:direction>
          <spirit:wireTypeDefs>
            <spirit:wireTypeDef>
              <spirit:typeName>std_logic</spirit:typeName>
              <spirit:viewNameRef>xilinx_anylanguagesynthesis</spirit:viewNameRef>
              <spirit:viewNameRef>xilinx_anylanguagebehavioralsimulation</spirit:viewNameRef>
            </spirit:wireTypeDef>
          </spirit:wireTypeDefs>
          <spirit:driver>
            <spirit:defaultValue spirit:format="long">0</spirit:defaultValue>
          </spirit:driver>
        </spirit:wire>
      </spirit:port>
      <spirit:port>
        <spirit:name>s_axi_ctrl_bresp</spirit:name>
        <spirit:wire>
          <spirit:direction>out</spirit:direction>
          <spirit:vector>
            <spirit:left spirit:format="long">1</spirit:left>
            <spirit:right spirit:format="long">0</spirit:right>
          </spirit:vector>
          <spirit:wireTypeDefs>
            <spirit:wireTypeDef>
              <spirit:typeName>std_logic_vector</spirit:typeName>
              <spirit:viewNameRef>xilinx_anylanguagesynthesis</spirit:viewNameRef>
              <spirit:viewNameRef>xilinx_anylanguagebehavioralsimulation</spirit:viewNameRef>
            </spirit:wireTypeDef>
          </spirit:wireTypeDefs>
        </spirit:wire>
      </spirit:port>
      <spirit:port>
        <spirit:name>s_axi_ctrl_arvalid</spirit:name>
        <spirit:wire>
          <spirit:direction>in</spirit:direction>
          <spirit:wireTypeDefs>
            <spirit:wireTypeDef>
              <spirit:typeName>std_logic</spirit:typeName>
              <spirit:viewNameRef>xilinx_anylanguagesynthesis</spirit:viewNameRef>
              <spirit:viewNameRef>xilinx_anylanguagebehavioralsimulation</spirit:viewNameRef>
            </spirit:wireTypeDef>
          </spirit:wireTypeDefs>
          <spirit:driver>
            <spirit:defaultValue spirit:format="long">0</spirit:defaultValue>
          </spirit:driver>
        </spirit:wire>
      </spirit:port>
      <spirit:port>
        <spirit:name>s_axi_ctrl_arready</spirit:name>
        <spirit:wire>
          <spirit:direction>out</spirit:direction>
          <spirit:wireTypeDefs>
            <spirit:wireTypeDef>
              <spirit:typeName>std_logic</spirit:typeName>
              <spirit:viewNameRef>xilinx_anylanguagesynthesis</spirit:viewNameRef>
              <spirit:viewNameRef>xilinx_anylanguagebehavioralsimulation</spirit:viewNameRef>
            </spirit:wireTypeDef>
          </spirit:wireTypeDefs>
        </spirit:wire>
      </spirit:port>
      <spirit:port>
        <spirit:name>s_axi_ctrl_araddr</spirit:name>
        <spirit:wire>
          <spirit:direction>in</spirit:direction>
          <spirit:vector>
            <spirit:left spirit:format="long">7</spirit:left>
            <spirit:right spirit:format="long">0</spirit:right>
          </spirit:vector>
          <spirit:wireTypeDefs>
            <spirit:wireTypeDef>
              <spirit:typeName>std_logic_vector</spirit:typeName>
              <spirit:viewNameRef>xilinx_anylanguagesynthesis</spirit:viewNameRef>
              <spirit:viewNameRef>xilinx_anylanguagebehavioralsimulation</spirit:viewNameRef>
            </spirit:wireTypeDef>
          </spirit:wireTypeDefs>
          <spirit:driver>
            <spirit:defaultValue spirit:format="long">0</spirit:defaultValue>
          </spirit:driver>
        </spirit:wire>
      </spirit:port>
      <spirit:port>
        <spirit:name>s_axi_ctrl_rvalid</spirit:name>
        <spirit:wire>
          <spirit:direction>out</spirit:direction>
          <spirit:wireTypeDefs>
            <spirit:wireTypeDef>
              <spirit:typeName>std_logic</spirit:typeName>
              <spirit:viewNameRef>xilinx_anylanguagesynthesis</spirit:viewNameRef>
              <spirit:viewNameRef>xilinx_anylanguagebehavioralsimulation</spirit:viewNameRef>
            </spirit:wireTypeDef>
          </spirit:wireTypeDefs>
        </spirit:wire>
      </spirit:port>
      <spirit:port>
        <spirit:name>s_axi_ctrl_rready</spirit:name>
        <spirit:wire>
          <spirit:direction>in</spirit:direction>
          <spirit:wireTypeDefs>
            <spirit:wireTypeDef>
              <spirit:typeName>std_logic</spirit:typeName>
              <spirit:viewNameRef>xilinx_anylanguagesynthesis</spirit:viewNameRef>
              <spirit:viewNameRef>xilinx_anylanguagebehavioralsimulation</spirit:viewNameRef>
            </spirit:wireTypeDef>
          </spirit:wireTypeDefs>
          <spirit:driver>
            <spirit:defaultValue spirit:format="long">0</spirit:defaultValue>
          </spirit:driver>
        </spirit:wire>
      </spirit:port>
      <spirit:port>
        <spirit:name>s_axi_ctrl_rdata</spirit:name>
        <spirit:wire>
          <spirit:direction>out</spirit:direction>
          <spirit:vector>
            <spirit:left spirit:format="long">31</spirit:left>
            <spirit:right spirit:format="long">0</spirit:right>
          </spirit:vector>
          <spirit:wireTypeDefs>
            <spirit:wireTypeDef>
              <spirit:typeName>std_logic_vector</spirit:typeName>
              <spirit:viewNameRef>xilinx_anylanguagesynthesis</spirit:viewNameRef>
              <spirit:viewNameRef>xilinx_anylanguagebehavioralsimulation</spirit:viewNameRef>
            </spirit:wireTypeDef>
          </spirit:wireTypeDefs>
        </spirit:wire>
      </spirit:port>
      <spirit:port>
        <spirit:name>s_axi_ctrl_rresp</spirit:name>
        <spirit:wire>
          <spirit:direction>out</spirit:direction>
          <spirit:vector>
            <spirit:left spirit:format="long">1</spirit:left>
            <spirit:right spirit:format="long">0</spirit:right>
          </spirit:vector>
          <spirit:wireTypeDefs>
            <spirit:wireTypeDef>
              <spirit:typeName>std_logic_vector</spirit:typeName>
              <spirit:viewNameRef>xilinx_anylanguagesynthesis</spirit:viewNameRef>
              <spirit:viewNameRef>xilinx_anylanguagebehavioralsimulation</spirit:viewNameRef>
            </spirit:wireTypeDef>
          </spirit:wireTypeDefs>
        </spirit:wire>
      </spirit:port>
      <spirit:port>
        <spirit:name>irq</spirit:name>
        <spirit:wire>
          <spirit:direction>out</spirit:direction>
          <spirit:wireTypeDefs>
            <spirit:wireTypeDef>
              <spirit:typeName>std_logic</spirit:typeName>
              <spirit:viewNameRef>xilinx_anylanguagesynthesis</spirit:viewNameRef>
              <spirit:viewNameRef>xilinx_anylanguagebehavioralsimulation</spirit:viewNameRef>
            </spirit:wireTypeDef>
          </spirit:wireTypeDefs>
        </spirit:wire>
      </spirit:port>
      <spirit:port>
        <spirit:name>acr_cts_in</spirit:name>
        <spirit:wire>
          <spirit:direction>in</spirit:direction>
          <spirit:vector>
            <spirit:left spirit:format="long">19</spirit:left>
            <spirit:right spirit:format="long">0</spirit:right>
          </spirit:vector>
          <spirit:wireTypeDefs>
            <spirit:wireTypeDef>
              <spirit:typeName>std_logic_vector</spirit:typeName>
              <spirit:viewNameRef>xilinx_anylanguagesynthesis</spirit:viewNameRef>
              <spirit:viewNameRef>xilinx_anylanguagebehavioralsimulation</spirit:viewNameRef>
            </spirit:wireTypeDef>
          </spirit:wireTypeDefs>
        </spirit:wire>
      </spirit:port>
      <spirit:port>
        <spirit:name>acr_n_in</spirit:name>
        <spirit:wire>
          <spirit:direction>in</spirit:direction>
          <spirit:vector>
            <spirit:left spirit:format="long">19</spirit:left>
            <spirit:right spirit:format="long">0</spirit:right>
          </spirit:vector>
          <spirit:wireTypeDefs>
            <spirit:wireTypeDef>
              <spirit:typeName>std_logic_vector</spirit:typeName>
              <spirit:viewNameRef>xilinx_anylanguagesynthesis</spirit:viewNameRef>
              <spirit:viewNameRef>xilinx_anylanguagebehavioralsimulation</spirit:viewNameRef>
            </spirit:wireTypeDef>
          </spirit:wireTypeDefs>
        </spirit:wire>
      </spirit:port>
      <spirit:port>
        <spirit:name>acr_valid_in</spirit:name>
        <spirit:wire>
          <spirit:direction>in</spirit:direction>
          <spirit:wireTypeDefs>
            <spirit:wireTypeDef>
              <spirit:typeName>std_logic</spirit:typeName>
              <spirit:viewNameRef>xilinx_anylanguagesynthesis</spirit:viewNameRef>
              <spirit:viewNameRef>xilinx_anylanguagebehavioralsimulation</spirit:viewNameRef>
            </spirit:wireTypeDef>
          </spirit:wireTypeDefs>
        </spirit:wire>
      </spirit:port>
      <spirit:port>
        <spirit:name>fifo_datacount_in</spirit:name>
        <spirit:wire>
          <spirit:direction>in</spirit:direction>
          <spirit:vector>
            <spirit:left spirit:format="long">11</spirit:left>
            <spirit:right spirit:format="long">0</spirit:right>
          </spirit:vector>
          <spirit:wireTypeDefs>
            <spirit:wireTypeDef>
              <spirit:typeName>std_logic_vector</spirit:typeName>
              <spirit:viewNameRef>xilinx_anylanguagesynthesis</spirit:viewNameRef>
              <spirit:viewNameRef>xilinx_anylanguagebehavioralsimulation</spirit:viewNameRef>
            </spirit:wireTypeDef>
          </spirit:wireTypeDefs>
        </spirit:wire>
      </spirit:port>
      <spirit:port>
        <spirit:name>aud_clk_out</spirit:name>
        <spirit:wire>
          <spirit:direction>out</spirit:direction>
          <spirit:wireTypeDefs>
            <spirit:wireTypeDef>
              <spirit:typeName>std_logic</spirit:typeName>
              <spirit:viewNameRef>xilinx_anylanguagesynthesis</spirit:viewNameRef>
              <spirit:viewNameRef>xilinx_anylanguagebehavioralsimulation</spirit:viewNameRef>
            </spirit:wireTypeDef>
          </spirit:wireTypeDefs>
        </spirit:wire>
      </spirit:port>
    </spirit:ports>
  </spirit:model>
  <spirit:fileSets>
    <spirit:fileSet>
      <spirit:name>xilinx_xpgui_view_fileset</spirit:name>
      <spirit:file>
        <spirit:name>xgui/audio_clock_recovery_unit_v1_0.tcl</spirit:name>
        <spirit:fileType>tclSource</spirit:fileType>
        <spirit:userFileType>XGUI_VERSION_2</spirit:userFileType>
      </spirit:file>
    </spirit:fileSet>
    <spirit:fileSet>
      <spirit:name>xilinx_anylanguagebehavioralsimulation_view_fileset</spirit:name>
      <spirit:file>
        <spirit:name>hdl/audio_clock_recovery_unit_v1_0_rfs.sv</spirit:name>
        <spirit:fileType>systemVerilogSource</spirit:fileType>
        <spirit:userFileType>USED_IN_ipstatic</spirit:userFileType>
      </spirit:file>
    </spirit:fileSet>
    <spirit:fileSet>
      <spirit:name>xilinx_anylanguagesynthesis_view_fileset</spirit:name>
      <spirit:file>
        <spirit:name>hdl/src/verilog/audio_clock_recovery_ooc.xdc</spirit:name>
        <spirit:userFileType>xdc</spirit:userFileType>
        <spirit:userFileType>USED_IN_out_of_context</spirit:userFileType>
      </spirit:file>
      <spirit:file>
        <spirit:name>hdl/audio_clock_recovery_unit_v1_0_rfs.sv</spirit:name>
        <spirit:fileType>systemVerilogSource</spirit:fileType>
        <spirit:userFileType>CHECKSUM_ebd537ff</spirit:userFileType>
      </spirit:file>
    </spirit:fileSet>
  </spirit:fileSets>
  <spirit:description>Audio Clock Recovery Unit</spirit:description>
  <spirit:parameters>
    <spirit:parameter>
      <spirit:name>Component_Name</spirit:name>
      <spirit:value spirit:resolve="user" spirit:id="PARAM_VALUE.Component_Name" spirit:order="1">audio_clock_recovery_unit_v1_0</spirit:value>
    </spirit:parameter>
  </spirit:parameters>
  <spirit:vendorExtensions>
    <xilinx:coreExtensions>
      <xilinx:taxonomies>
        <xilinx:taxonomy>/UserIP</xilinx:taxonomy>
      </xilinx:taxonomies>
      <xilinx:displayName>audio_clock_recovery</xilinx:displayName>
      <xilinx:autoFamilySupportLevel>level_2</xilinx:autoFamilySupportLevel>
      <xilinx:xpmLibraries>
        <xilinx:xpmLibrary>XPM_CDC</xilinx:xpmLibrary>
      </xilinx:xpmLibraries>
      <xilinx:vendorDisplayName>xilinx</xilinx:vendorDisplayName>
      <xilinx:vendorURL>http://www.xilinx.com</xilinx:vendorURL>
      <xilinx:coreRevision>0</xilinx:coreRevision>
      <xilinx:coreCreationDateTime>2017-08-10T12:01:31Z</xilinx:coreCreationDateTime>
    </xilinx:coreExtensions>
    <xilinx:packagingInfo>
      <xilinx:xilinxVersion>2017.3.0</xilinx:xilinxVersion>
      <xilinx:checksum xilinx:scope="busInterfaces" xilinx:value="70538592"/>
      <xilinx:checksum xilinx:scope="fileGroups" xilinx:value="f349c038"/>
      <xilinx:checksum xilinx:scope="ports" xilinx:value="9f29988e"/>
      <xilinx:checksum xilinx:scope="parameters" xilinx:value="c26a5c7d"/>
    </xilinx:packagingInfo>
  </spirit:vendorExtensions>
</spirit:component>
